zim_dictionary_server.py
zim_dictionary_server-1.0.1.dist-info/entry_points.txt
zim_dictionary_server-1.0.1.dist-info/licenses/LICENSE
zim_dictionary_server-1.0.1.dist-info/WHEEL
zim_dictionary_server-1.0.1.dist-info/METADATA
zim_dictionary_server-1.0.1.dist-info/RECORD
