Metadata-Version: 2.4
Name: zim-dictionary-server
Version: 1.0.1
Summary: Serves contents of ZIM archives in a way optimized for convenient dictionary lookup.
Keywords: zim,dictionary
Author: Tomasz Buczyński
Requires-Python: ~= 3.13
License-Expression: AGPL-3.0-or-later
Classifier: Development Status :: 5 - Production/Stable
Classifier: Intended Audience :: End Users/Desktop
Classifier: Operating System :: OS Independent
Classifier: Programming Language :: Python :: 3
Classifier: Topic :: Utilities
License-File: LICENSE
Requires-Dist: libzim ~= 3.8
Project-URL: Repository, https://codeberg.org/tomekb234/zim-dictionary-server
